anndatavis/__init__.py
anndatavis/anndata_visualization.py
anndatavis-0.0.7.dist-info/LICENSE
anndatavis-0.0.7.dist-info/METADATA
anndatavis-0.0.7.dist-info/WHEEL
anndatavis-0.0.7.dist-info/top_level.txt
anndatavis-0.0.7.dist-info/RECORD
