Metadata-Version: 2.1
Name: anndatavis
Version: 0.0.7
Summary: anndatavis
Home-page: UNKNOWN
Author: Yochay Tzur
Author-email: yochaytzur@gmail.com
License: UNKNOWN
Keywords: python,anndata,single cell RNA
Platform: UNKNOWN
Classifier: Development Status :: 3 - Alpha
Classifier: Intended Audience :: Education
Classifier: Programming Language :: Python :: 3
Classifier: Operating System :: MacOS :: MacOS X
Classifier: Operating System :: Microsoft :: Windows
License-File: LICENSE
Requires-Dist: anndata
Requires-Dist: kaleido
Requires-Dist: plotly
